{
  "/_app": "pages/_app.js",
  "/_error": "pages/_error.js",
  "/ai-assistant": "pages/ai-assistant.js",
  "/_document": "pages/_document.js",
  "/analytics": "pages/analytics.js",
  "/api/ai-assistant": "pages/api/ai-assistant.js",
  "/api/send-notification-email": "pages/api/send-notification-email.js",
  "/api/create-checkout-session": "pages/api/create-checkout-session.js",
  "/api/whatsapp-callback": "pages/api/whatsapp-callback.js",
  "/cgv": "pages/cgv.js",
  "/appointments": "pages/appointments.js",
  "/conversation/[id]": "pages/conversation/[id].js",
  "/clients": "pages/clients.js",
  "/dashboard": "pages/dashboard.js",
  "/forgot-password": "pages/forgot-password.js",
  "/login": "pages/login.js",
  "/": "pages/index.js",
  "/market-insights": "pages/market-insights.js",
  "/menu": "pages/menu.js",
  "/onboarding": "pages/onboarding.js",
  "/partners": "pages/partners.js",
  "/payment": "pages/payment.js",
  "/privacy": "pages/privacy.js",
  "/settings": "pages/settings.js",
  "/subscription-success": "pages/subscription-success.js",
  "/signup": "pages/signup.js",
  "/tutorial": "pages/tutorial.js",
  "/api/whatsapp": "pages/api/whatsapp.js",
  "/api/stripe-webhook": "pages/api/stripe-webhook.js",
  "/api/bot": "pages/api/bot.js",
  "/api/webhook": "pages/api/webhook.js"
}